csvlineparser/__init__.py
csvlineparser/clientutils/__init__.py
csvlineparser/clientutils/__main__.py
csvlineparser/clientutils/aware_csv_context_provider.py
csvlineparser/clientutils/csv_cleaner_consumer.py
csvlineparser/clientutils/csv_console_consumer.py
csvlineparser/clientutils/csv_file_logger.py
csvlineparser/clientutils/file_handler.py
csvlineparser/core/__init__.py
csvlineparser/core/__main__.py
csvlineparser/core/char_tokenizer.py
csvlineparser/core/char_tokenizer_interface.py
csvlineparser/core/column_expander.py
csvlineparser/core/csv_consumer_interface.py
csvlineparser/core/csv_context_provider.py
csvlineparser/core/csv_data_type_mapping.py
csvlineparser/core/csv_parser.py
csvlineparser/core/csvlineparser.py
csvlineparser/core/default_parser_config.py
csvlineparser/core/exceptions.py
csvlineparser/core/field_splitter.py
csvlineparser/core/multi_consumer.py
csvlineparser/core/parser_config.py
csvlineparser/excelexport/__init__.py
csvlineparser/excelexport/__main__.py
csvlineparser/excelexport/csv_to_excel_exporter.py
csvlineparser-1.0.0.dist-info/METADATA
csvlineparser-1.0.0.dist-info/WHEEL
csvlineparser-1.0.0.dist-info/licenses/LICENSE
csvlineparser-1.0.0.dist-info/RECORD
