Metadata-Version: 2.1
Name: csvlineparser
Version: 1.0.0
Summary: A BNF grammar based CSV Parser that cleans up with messy CSV files, with optional Excel export
Project-URL: Homepage, https://github.com/raoulsson/csvlineparser
Author-email: raoulsson <hello@raoulsson.com>
License-File: LICENSE
Classifier: License :: OSI Approved :: MIT License
Classifier: Operating System :: OS Independent
Classifier: Programming Language :: Python :: 3
Requires-Python: >=3.7
